campers/__init__.py
campers/__main__.py
campers/constants.py
campers/lifecycle.py
campers/py.typed
campers/session.py
campers/templates.py
campers/utils.py
campers/cli/__init__.py
campers/cli/main.py
campers/cli/parsing.py
campers/core/__init__.py
campers/core/cleanup.py
campers/core/config.py
campers/core/interfaces.py
campers/core/run_executor.py
campers/core/signals.py
campers/core/utils.py
campers/logging/__init__.py
campers/logging/filters.py
campers/logging/formatters.py
campers/logging/handlers.py
campers/providers/__init__.py
campers/providers/exceptions.py
campers/providers/aws/__init__.py
campers/providers/aws/ami.py
campers/providers/aws/client_factory.py
campers/providers/aws/compute.py
campers/providers/aws/constants.py
campers/providers/aws/errors.py
campers/providers/aws/keypair.py
campers/providers/aws/network.py
campers/providers/aws/pricing.py
campers/providers/aws/pricing_parsers.py
campers/providers/aws/setup.py
campers/providers/aws/ssh.py
campers/providers/aws/utils.py
campers/services/__init__.py
campers/services/ansible.py
campers/services/portforward.py
campers/services/ssh.py
campers/services/sync.py
campers/services/validation.py
campers/tui/__init__.py
campers/tui/app.py
campers/tui/exit_modal.py
campers/tui/instance_overview_widget.py
campers/tui/styling.py
campers/tui/terminal.py
campers/tui/widgets.py
campers/tui/widgets/__init__.py
campers/tui/widgets/context_menu.py
campers/tui/widgets/labeled_value.py
campers/tui/widgets/search_input.py
campers/tui/widgets/selectable_log.py
campers/tui/widgets/selection.py
campers-0.1.5.dist-info/licenses/LICENSE
campers-0.1.5.dist-info/METADATA
campers-0.1.5.dist-info/WHEEL
campers-0.1.5.dist-info/entry_points.txt
campers-0.1.5.dist-info/top_level.txt
campers-0.1.5.dist-info/RECORD
