Metadata-Version: 2.4
Name: campers
Version: 0.1.5
Summary: CLI tool for managing remote development environments on the cloud
License: MIT
Project-URL: Homepage, https://github.com/kamilc/campers
Project-URL: Repository, https://github.com/kamilc/campers
Project-URL: Issues, https://github.com/kamilc/campers/issues
Keywords: development,remote,cloud,ssh,ansible,aws,ec2
Classifier: Development Status :: 4 - Beta
Classifier: Environment :: Console
Classifier: Intended Audience :: Developers
Classifier: License :: OSI Approved :: MIT License
Classifier: Operating System :: OS Independent
Classifier: Programming Language :: Python :: 3
Classifier: Programming Language :: Python :: 3.12
Classifier: Topic :: Software Development
Classifier: Topic :: System :: Systems Administration
Requires-Python: >=3.12
License-File: LICENSE
Requires-Dist: ansible>=8.0.0
Requires-Dist: boto3>=1.40.42
Requires-Dist: fire>=0.7.1
Requires-Dist: omegaconf>=2.3.0
Requires-Dist: paramiko<4.0.0,>=3.0.0
Requires-Dist: python-dotenv>=1.2.1
Requires-Dist: pyperclip>=1.9.0
Requires-Dist: pyyaml>=6.0.3
Requires-Dist: requests>=2.32.5
Requires-Dist: rich>=14.1.0
Requires-Dist: sshtunnel>=0.4.0
Requires-Dist: tenacity>=9.1.2
Requires-Dist: textual>=6.2.0
Dynamic: license-file
